{
  "body": {
    "channel": "CURRENT",
    "deployment": {
      "kind": "BUNDLE",
      "metadata_file_path": "/Workspace/Users/[USERNAME]/.bundle/run_as/t_user_name_different/state/metadata.json"
    },
    "edition": "ADVANCED",
    "libraries": [
      {
        "notebook": {
          "path": "/Workspace/Users/[USERNAME]/.bundle/run_as/t_user_name_different/files/dlt/nyc_taxi_loader"
        }
      }
    ],
    "name": "nyc taxi loader",
    "run_as": {
      "user_name": "different@databricks.com"
    }
  },
  "method": "POST",
  "path": "/api/2.0/pipelines"
}
{
  "body": {
    "access_control_list": [
      {
        "permission_level": "CAN_VIEW",
        "service_principal_name": "my_service_principal"
      },
      {
        "permission_level": "CAN_VIEW",
        "user_name": "different@databricks.com"
      },
      {
        "permission_level": "IS_OWNER",
        "user_name": "[USERNAME]"
      }
    ]
  },
  "method": "PUT",
  "path": "/api/2.0/permissions/pipelines/[UUID]"
}
